IPD/__init__.py
IPD/__main__.py
IPD/data.py
IPD/gui.py
IPD/main.py
IPD/play.py
IPD/profiles.py
IPD/strategies.py
IPD_axelrod-1.1.0.dist-info/LICENSE
IPD_axelrod-1.1.0.dist-info/METADATA
IPD_axelrod-1.1.0.dist-info/WHEEL
IPD_axelrod-1.1.0.dist-info/top_level.txt
IPD_axelrod-1.1.0.dist-info/RECORD
